refactor_app/__init__.py
refactor_app/core/__init__.py
refactor_app/core/config.py
refactor_app/core/database/__init__.py
refactor_app/core/database/sqlite.py
refactor_app/core/logging_config.py
refactor_app/core/repositories/__init__.py
refactor_app/core/repositories/base_sensor_repository.py
refactor_app/core/services/__init__.py
refactor_app/core/services/base_noise_equivalent.py
refactor_app/core/services/base_noise_sensor_service.py
refactor_app/core/services/base_sensor_service.py
refactor_app/core/services/noise_event.py
refactor_app/noise_main.py
refactor_app/repositories/__init__.py
refactor_app/repositories/noise/__init__.py
refactor_app/repositories/noise/event_repository.py
refactor_app/repositories/noise/noise_repository.py
refactor_app/repositories/noise/notification_repository.py
refactor_app/repositories/producer_repository/__init__.py
refactor_app/schemas/__init__.py
refactor_app/schemas/noise_schemas.py
refactor_app/services/__init__.py
refactor_app/services/dust_services/__init__.py
refactor_app/services/noise_services/__init__.py
refactor_app/services/noise_services/event_service.py
refactor_app/services/noise_services/nti_service.py
refactor_app/services/noise_services/umik_service.py
refactor_app/utils/__init__.py
refactor_app/utils/calculate_utils.py
refactor_app/utils/nti_utils.py
refactor_app/utils/system_utils.py
refactor_app/utils/umik_utils.py
rabbitmq_umik_producers-0.1.0.dist-info/METADATA
rabbitmq_umik_producers-0.1.0.dist-info/WHEEL
rabbitmq_umik_producers-0.1.0.dist-info/entry_points.txt
rabbitmq_umik_producers-0.1.0.dist-info/RECORD
