Metadata-Version: 2.1
Name: rabbitmq_umik_producers
Version: 0.1.0
Summary: producers
Author: Yaroslav
Requires-Python: >=3.8,<4.0
Classifier: Programming Language :: Python :: 3
Classifier: Programming Language :: Python :: 3.8
Classifier: Programming Language :: Python :: 3.9
Classifier: Programming Language :: Python :: 3.10
Classifier: Programming Language :: Python :: 3.11
Classifier: Programming Language :: Python :: 3.12
Classifier: Programming Language :: Python :: 3.13
Requires-Dist: acoustics (>=0.2.6,<0.3.0)
Requires-Dist: aiosqlite (>=0.20.0,<0.21.0)
Requires-Dist: luma-core (==2.3.1)
Requires-Dist: minio (==7.2.7)
Requires-Dist: mypy (>=1.14.0,<2.0.0)
Requires-Dist: numpy (==1.24.4)
Requires-Dist: plotly (>=5.24.1,<6.0.0)
Requires-Dist: pyaudio (==0.2.14)
Requires-Dist: pydantic (==2.0.3)
Requires-Dist: pydantic-settings (==2.0.3)
Requires-Dist: pydub (==0.25.1)
Requires-Dist: pytest (==8.3.4)
Requires-Dist: pytz (==2021.3)
